{
    "members":
    [
        {
            "lastname":"Doukouré",
            "firstname":"Fernand Gilles Armel",
            "function":"Président",
            "gender":"Masculin",
            "email":"gilles.doukoure@harriste.com",
            "phone":"06.58.77.23.97",
            "address1":"4 Allé du Vercors",
            "address2":"",
            "zip_code":"94800",
            "city":"Villejuif",
            "avatar":""
        },
        {
            "lastname":"Késsé",
            "firstname":"Tia Gérard",
            "function":"Chargé Communication",
            "gender":"Masculin",
            "email":"gilles.doukoure@harriste.com",
            "phone":"06.58.77.23.97",
            "address1":"4 Allé du Vercors",
            "address2":"",
            "zip_code":"94800",
            "city":"Villejuif",
            "registration_number":"",
            "avatar":"tia_gerard_kesse.png"
        },
        {
            "lastname":"Tayé",
            "firstname":"Phillipe Sabine",
            "function":"Maître de Choeur",
            "gender":"Féminin",
            "email":"gilles.doukoure@harriste.com",
            "phone":"06.58.77.23.97",
            "address1":"4 Allé du Vercors",
            "address2":"",
            "zip_code":"94800",
            "city":"Villejuif",
            "registration_number":"",
            "avatar":""
        },
        {
            "lastname":"KASSI",
            "firstname":"Phillipe Sabine",
            "function":"Maître de Choeur",
            "gender":"Masculin",
            "email":"gilles.doukoure@harriste.com",
            "phone":"06.58.77.23.97",
            "address1":"4 Allé du Vercors",
            "address2":"",
            "zip_code":"94800",
            "registration_number":"",
            "city":"Villejuif",
            "avatar":""
        }
    ]
}